dxf2geo/__about__.py
dxf2geo/__init__.py
dxf2geo/extract.py
dxf2geo/visualise.py
dxf2geo-0.1.3.dist-info/licenses/LICENSE.txt
dxf2geo-0.1.3.dist-info/METADATA
dxf2geo-0.1.3.dist-info/WHEEL
dxf2geo-0.1.3.dist-info/top_level.txt
dxf2geo-0.1.3.dist-info/RECORD
