Metadata-Version: 2.4
Name: dxf2geo
Version: 0.1.3
Summary: Convert CAD DXF data into geospatial formats and visualisations using GeoPandas/Pyogrio.
Author: Keiran Suchak
Project-URL: Homepage, https://github.com/ksuchak1990/dxf2geo
Project-URL: Repository, https://github.com/ksuchak1990/dxf2geo
Project-URL: Issues, https://github.com/ksuchak1990/dxf2geo/issues
Keywords: GDAL,DXF,geospatial,GIS,vector,conversion
Classifier: Programming Language :: Python :: 3 :: Only
Classifier: Programming Language :: Python :: 3.10
Classifier: Programming Language :: Python :: 3.11
Classifier: Programming Language :: Python :: 3.12
Classifier: Programming Language :: Python :: 3.13
Classifier: License :: OSI Approved :: MIT License
Classifier: Operating System :: OS Independent
Classifier: Topic :: Scientific/Engineering :: GIS
Requires-Python: >=3.10
License-File: LICENSE.txt
Requires-Dist: geopandas>=1.0
Requires-Dist: pyogrio>=0.11
Requires-Dist: shapely>=2.0
Requires-Dist: pandas>=2.0
Requires-Dist: plotly>=5
Requires-Dist: tqdm>=4.66
Provides-Extra: dev
Requires-Dist: pytest; extra == "dev"
Requires-Dist: pytest-mock; extra == "dev"
Requires-Dist: ruff; extra == "dev"
Requires-Dist: black; extra == "dev"
Requires-Dist: build; extra == "dev"
Requires-Dist: twine; extra == "dev"
Dynamic: license-file
